opensearch_py_ml/__init__.py
opensearch_py_ml/_version.py
opensearch_py_ml/actions.py
opensearch_py_ml/arithmetics.py
opensearch_py_ml/common.py
opensearch_py_ml/conftest.py
opensearch_py_ml/dataframe.py
opensearch_py_ml/etl.py
opensearch_py_ml/field_mappings.py
opensearch_py_ml/filter.py
opensearch_py_ml/groupby.py
opensearch_py_ml/index.py
opensearch_py_ml/ndframe.py
opensearch_py_ml/operations.py
opensearch_py_ml/py.typed
opensearch_py_ml/query.py
opensearch_py_ml/query_compiler.py
opensearch_py_ml/series.py
opensearch_py_ml/tasks.py
opensearch_py_ml/utils.py
opensearch_py_ml/ml_commons/__init__.py
opensearch_py_ml/ml_commons/ml_common_utils.py
opensearch_py_ml/ml_commons/ml_commons_client.py
opensearch_py_ml/ml_commons/model_access_control.py
opensearch_py_ml/ml_commons/model_connector.py
opensearch_py_ml/ml_commons/model_execute.py
opensearch_py_ml/ml_commons/model_uploader.py
opensearch_py_ml/ml_commons/validators.py
opensearch_py_ml/ml_commons/cli/__init__.py
opensearch_py_ml/ml_commons/cli/ai_connector_helper.py
opensearch_py_ml/ml_commons/cli/aws_config.py
opensearch_py_ml/ml_commons/cli/cli_base.py
opensearch_py_ml/ml_commons/cli/connector_list.py
opensearch_py_ml/ml_commons/cli/connector_manager.py
opensearch_py_ml/ml_commons/cli/iam_role_helper.py
opensearch_py_ml/ml_commons/cli/ml_cli.py
opensearch_py_ml/ml_commons/cli/ml_setup.py
opensearch_py_ml/ml_commons/cli/model_manager.py
opensearch_py_ml/ml_commons/cli/opensearch_domain_config.py
opensearch_py_ml/ml_commons/cli/secret_helper.py
opensearch_py_ml/ml_commons/cli/ml_models/__init__.py
opensearch_py_ml/ml_commons/cli/ml_models/aleph_alpha_model.py
opensearch_py_ml/ml_commons/cli/ml_models/azure_openai_model.py
opensearch_py_ml/ml_commons/cli/ml_models/bedrock_converse_model.py
opensearch_py_ml/ml_commons/cli/ml_models/bedrock_model.py
opensearch_py_ml/ml_commons/cli/ml_models/cohere_model.py
opensearch_py_ml/ml_commons/cli/ml_models/comprehend_model.py
opensearch_py_ml-1.3.0.dist-info/licenses/LICENSE
opensearch_py_ml-1.3.0.dist-info/licenses/NOTICE
opensearch_py_ml-1.3.0.dist-info/METADATA
opensearch_py_ml-1.3.0.dist-info/WHEEL
opensearch_py_ml-1.3.0.dist-info/entry_points.txt
opensearch_py_ml-1.3.0.dist-info/top_level.txt
opensearch_py_ml-1.3.0.dist-info/RECORD
