Metadata-Version: 2.4
Name: opensearch_py_ml
Version: 1.3.0
Summary: Python Client and Toolkit for DataFrames, Big Data, Machine Learning and ETL in OpenSearch
Home-page: https://github.com/opensearch-project/opensearch-py-ml
Author: Dhrubo Saha
Author-email: dhrubo@amazon.com, 
Maintainer: Dhrubo Saha, Yaliang Wu, Alexander Greaves-Tunnell, Sicheng Song, Jing Zhang, Bhavana Goud Ramaram, Yerzhaisang Taskali, Nathalie Jonathan
Maintainer-email: dhrubo@amazon.com, ylwu@amazon.com, greaa@amazon.com, seasonsg@amazon.com, jngz@amazon.com, rbhavna@amazon.com, tasqali1697@gmail.com, nathhjo@amazon.com
License: Apache-2.0
Project-URL: Source Code, https://github.com/opensearch-project/opensearch-py-ml
Project-URL: Issue Tracker, https://github.com/opensearch-project/opensearch-py-ml/issues
Keywords: Opensearch opensearch_py_ml pandas python
Classifier: Development Status :: 5 - Production/Stable
Classifier: License :: OSI Approved :: Apache Software License
Classifier: Environment :: Console
Classifier: Operating System :: OS Independent
Classifier: Intended Audience :: Developers
Classifier: Intended Audience :: Science/Research
Classifier: Programming Language :: Python
Classifier: Programming Language :: Python :: 3
Classifier: Programming Language :: Python :: 3 :: Only
Classifier: Programming Language :: Python :: 3.11
Classifier: Programming Language :: Python :: 3.12
Classifier: Programming Language :: Python :: 3.13
Classifier: Topic :: Scientific/Engineering
Requires-Python: >=3.11
License-File: LICENSE
License-File: NOTICE
Requires-Dist: opensearch-py>=2
Requires-Dist: pandas!=2.1.0,<2.3,>=1.5.2
Requires-Dist: matplotlib<4,>=3.6.0
Requires-Dist: numpy>=2.3.2
Requires-Dist: deprecated<2,>=1.2.14
Requires-Dist: boto3>=1.26.0
Requires-Dist: botocore>=1.29.0
Requires-Dist: requests>=2.28.0
Requires-Dist: requests-aws4auth>=1.1.0
Requires-Dist: colorama>=0.4.6
Requires-Dist: rich>=13.5.2
Requires-Dist: pyyaml>=6.0.2
Provides-Extra: all
Dynamic: author
Dynamic: author-email
Dynamic: classifier
Dynamic: description
Dynamic: description-content-type
Dynamic: home-page
Dynamic: keywords
Dynamic: license
Dynamic: license-file
Dynamic: maintainer
Dynamic: maintainer-email
Dynamic: project-url
Dynamic: provides-extra
Dynamic: requires-dist
Dynamic: requires-python
Dynamic: summary
